dra/__init__.py
dra/dose_response_analyzer.py
dose_response_analyzer-0.1.1.dist-info/entry_points.txt
dose_response_analyzer-0.1.1.dist-info/METADATA
dose_response_analyzer-0.1.1.dist-info/WHEEL
dose_response_analyzer-0.1.1.dist-info/RECORD
